AUTHORS
COPYING
MANIFEST
MANIFEST.in
README
TODO
eagle.py
generate-docs.sh
setup.py
./eagle.py
docs/eagle.html
docs/api/index.html
docs/api/private/__builtin__.object-class.html
docs/api/private/__builtin__.type-class.html
docs/api/private/eagle-module.html
docs/api/private/eagle.AboutButton-class.html
docs/api/private/eagle.AboutDialog-class.html
docs/api/private/eagle.App-class.html
docs/api/private/eagle.AutoGenId-class.html
docs/api/private/eagle.Button-class.html
docs/api/private/eagle.Canvas-class.html
docs/api/private/eagle.CheckBox-class.html
docs/api/private/eagle.CloseButton-class.html
docs/api/private/eagle.Color-class.html
docs/api/private/eagle.DebugDialog-class.html
docs/api/private/eagle.Entry-class.html
docs/api/private/eagle.FileChooser-class.html
docs/api/private/eagle.Font-class.html
docs/api/private/eagle.Group-class.html
docs/api/private/eagle.HSeparator-class.html
docs/api/private/eagle.HelpButton-class.html
docs/api/private/eagle.HelpDialog-class.html
docs/api/private/eagle.Image-class.html
docs/api/private/eagle.IntSpin-class.html
docs/api/private/eagle.Label-class.html
docs/api/private/eagle.OpenFileButton-class.html
docs/api/private/eagle.Password-class.html
docs/api/private/eagle.PreferencesButton-class.html
docs/api/private/eagle.PreferencesDialog-class.html
docs/api/private/eagle.Progress-class.html
docs/api/private/eagle.QuitButton-class.html
docs/api/private/eagle.SaveFileButton-class.html
docs/api/private/eagle.SelectFolderButton-class.html
docs/api/private/eagle.Selection-class.html
docs/api/private/eagle.Spin-class.html
docs/api/private/eagle.UIntSpin-class.html
docs/api/private/eagle.VSeparator-class.html
docs/api/private/eagle._EGDataWidget-class.html
docs/api/private/eagle._EGObject-class.html
docs/api/private/eagle._EGWidLabelEntry-class.html
docs/api/private/eagle._EGWidget-class.html
docs/api/private/eagle._HPanel-class.html
docs/api/private/eagle._Panel-class.html
docs/api/private/eagle._Table-class.html
eagle.egg-info/PKG-INFO
eagle.egg-info/SOURCES.txt
eagle.egg-info/requires.txt
eagle.egg-info/top_level.txt
