Metadata-Version: 1.0
Name: eagle
Version: 0.2
Summary: Eagle is an abstraction layer atop Graphical Toolkits focused on
